poetry_plugin_version/__init__.py
poetry_plugin_version/api.py
poetry_plugin_version/patch.py
poetry_plugin_version/plugin.py
poetry_plugin_version/states.py
poetry_plugin_version/utils.py
poetry_plugin_version-0.5.5.dist-info/LICENSE
poetry_plugin_version-0.5.5.dist-info/METADATA
poetry_plugin_version-0.5.5.dist-info/WHEEL
poetry_plugin_version-0.5.5.dist-info/entry_points.txt
poetry_plugin_version-0.5.5.dist-info/RECORD
